delphin/__about__.py
delphin/__main__.py
delphin/ace.py
delphin/commands.py
delphin/derivation.py
delphin/edm.py
delphin/exceptions.py
delphin/hierarchy.py
delphin/highlight.py
delphin/interface.py
delphin/itsdb.py
delphin/lnk.py
delphin/main.py
delphin/predicate.py
delphin/repp.py
delphin/scope.py
delphin/sembase.py
delphin/semi.py
delphin/tdl.py
delphin/tfs.py
delphin/tokens.py
delphin/tsdb.py
delphin/tsql.py
delphin/util.py
delphin/variable.py
delphin/vpm.py
delphin/cli/compare.py
delphin/cli/convert.py
delphin/cli/edm.py
delphin/cli/mkprof.py
delphin/cli/process.py
delphin/cli/repp.py
delphin/cli/select.py
delphin/codecs/ace.py
delphin/codecs/dmrsjson.py
delphin/codecs/dmrspenman.py
delphin/codecs/dmrstikz.py
delphin/codecs/dmrx.py
delphin/codecs/eds.py
delphin/codecs/edsjson.py
delphin/codecs/edspenman.py
delphin/codecs/indexedmrs.py
delphin/codecs/mrsjson.py
delphin/codecs/mrsprolog.py
delphin/codecs/mrx.py
delphin/codecs/simpledmrs.py
delphin/codecs/simplemrs.py
delphin/dmrs/__init__.py
delphin/dmrs/_dmrs.py
delphin/dmrs/_exceptions.py
delphin/dmrs/_operations.py
delphin/eds/__init__.py
delphin/eds/_eds.py
delphin/eds/_exceptions.py
delphin/eds/_operations.py
delphin/mrs/__init__.py
delphin/mrs/_exceptions.py
delphin/mrs/_mrs.py
delphin/mrs/_operations.py
delphin/web/__init__.py
delphin/web/client.py
delphin/web/server.py
pydelphin-1.10.0.dist-info/METADATA
pydelphin-1.10.0.dist-info/WHEEL
pydelphin-1.10.0.dist-info/entry_points.txt
pydelphin-1.10.0.dist-info/licenses/LICENSE
pydelphin-1.10.0.dist-info/RECORD
