Metadata-Version: 2.4
Name: PyDelphin
Version: 1.10.0
Summary: Libraries and scripts for DELPH-IN data
Project-URL: Homepage, https://github.com/delph-in/pydelphin
Project-URL: Documentation, https://pydelphin.readthedocs.io
Project-URL: Changelog, https://github.com/delph-in/pydelphin/blob/main/CHANGELOG.md
Author-email: Michael Wayne Goodman <goodman.m.w@gmail.com>
License-Expression: MIT
License-File: LICENSE
Keywords: delph-in,hpsg,linguistics,nlp,semantics
Classifier: Development Status :: 5 - Production/Stable
Classifier: Environment :: Console
Classifier: Intended Audience :: Developers
Classifier: Intended Audience :: Information Technology
Classifier: Intended Audience :: Science/Research
Classifier: License :: OSI Approved :: MIT License
Classifier: Programming Language :: Python :: 3
Classifier: Programming Language :: Python :: 3.9
Classifier: Programming Language :: Python :: 3.10
Classifier: Programming Language :: Python :: 3.11
Classifier: Programming Language :: Python :: 3.12
Classifier: Programming Language :: Python :: 3.13
Classifier: Topic :: Scientific/Engineering :: Information Analysis
Classifier: Topic :: Software Development :: Libraries :: Python Modules
Classifier: Topic :: Text Processing :: Linguistic
Classifier: Topic :: Utilities
Requires-Python: >=3.9
Requires-Dist: penman
Requires-Dist: progress
Requires-Dist: pygments
Provides-Extra: repp
Requires-Dist: regex; extra == 'repp'
Provides-Extra: web
Requires-Dist: falcon; extra == 'web'
Requires-Dist: requests; extra == 'web'
